exoppy/__init__.py
exoppy/lightcurve.py
exoppy-0.0.1.dist-info/LICENSE
exoppy-0.0.1.dist-info/METADATA
exoppy-0.0.1.dist-info/WHEEL
exoppy-0.0.1.dist-info/top_level.txt
exoppy-0.0.1.dist-info/RECORD
