Metadata-Version: 2.1
Name: exoppy
Version: 0.0.1
License-File: LICENSE
Requires-Dist: numpy
